avesta/.git/COMMIT_EDITMSG
avesta/.git/FETCH_HEAD
avesta/.git/HEAD
avesta/.git/ORIG_HEAD
avesta/.git/config
avesta/.git/description
avesta/.git/hooks/applypatch-msg.sample
avesta/.git/hooks/commit-msg.sample
avesta/.git/hooks/fsmonitor-watchman.sample
avesta/.git/hooks/post-update.sample
avesta/.git/hooks/pre-applypatch.sample
avesta/.git/hooks/pre-commit.sample
avesta/.git/hooks/pre-merge-commit.sample
avesta/.git/hooks/pre-push.sample
avesta/.git/hooks/pre-rebase.sample
avesta/.git/hooks/pre-receive.sample
avesta/.git/hooks/prepare-commit-msg.sample
avesta/.git/hooks/push-to-checkout.sample
avesta/.git/hooks/update.sample
avesta/.git/index
avesta/.git/info/exclude
avesta/.git/logs/HEAD
avesta/.git/logs/refs/heads/main
avesta/.git/logs/refs/remotes/origin/HEAD
avesta/.git/logs/refs/remotes/origin/main
avesta/.git/objects/00/3fd8dd5827c1b23eb7077cb80827dc7c28f7dd
avesta/.git/objects/01/04381956a74095a22edc4ada793b1e110fb342
avesta/.git/objects/01/d77c7d44c6b4a097047b9a98f21c95bd0fd650
avesta/.git/objects/02/40c5e141bef1f6eaaeee211edb9f3fc9b0fb1b
avesta/.git/objects/02/be5739d3d058d3b72cbc0cdfac1c938cf044a6
avesta/.git/objects/03/20b1e01cd9225f94d568e1abb3832ca9d82e5f
avesta/.git/objects/03/ce00ca7bc6dc7c431a209aa296b228b1437e13
avesta/.git/objects/04/8cfcf608fc281c4dfaf56774b442580bd20ff4
avesta/.git/objects/05/b5bb8afd56aac6e4a3d35dc836f6ed60294959
avesta/.git/objects/06/2107b1d73862272fe0e3bb7fffcabfe36acb0f
avesta/.git/objects/09/7d767c1b7062192118fd75447e054ebace70ab
avesta/.git/objects/09/a5b9fd825deb94ff689b45d6328d3bc1bf67f5
avesta/.git/objects/0a/678d46ea6ba30bef4ccc9ad5f716f9a040a52b
avesta/.git/objects/0b/38d110ca2d5ec8b03f48660bb72f3802e921c8
avesta/.git/objects/0c/e50ef39957dce62ec1156cac0e05bd6ca2c528
avesta/.git/objects/0d/25fad689f3a64e043fc4888394b6e98b52c835
avesta/.git/objects/0e/688c24b27af652fd75511e888842181eaea4c1
avesta/.git/objects/10/7f108f8eafd50a440019646062c9e6eef999e9
avesta/.git/objects/11/5944463ede090c2e4fce2a0611fe91133ed93d
avesta-0.19.dist-info/WHEEL
avesta-0.19.dist-info/METADATA
avesta-0.19.dist-info/RECORD
