Metadata-Version: 2.1
Name: avesta
Version: 0.19
Summary: A Python library for text processing
Home-page: https://github.com/mfsadi/avesta
License: MIT
Author: Majid Fahandezi Sadi
Author-email: mfsadi.work@gmail.com
Requires-Python: >=3.10,<4.0
Classifier: License :: OSI Approved :: MIT License
Classifier: Programming Language :: Python :: 3
Classifier: Programming Language :: Python :: 3.10
Requires-Dist: Levenshtein (==0.25.0)
Requires-Dist: PersianStemmer (==1.0.0)
Requires-Dist: nltk (==3.9.1)
Requires-Dist: pandas (==2.2.0)
Requires-Dist: tqdm (==4.66.2)
Project-URL: Repository, https://github.com/mfsadi/avesta
